agentstack_sdk/__init__.py
agentstack_sdk/a2a/__init__.py
agentstack_sdk/a2a/extensions/__init__.py
agentstack_sdk/a2a/extensions/auth/__init__.py
agentstack_sdk/a2a/extensions/auth/oauth/__init__.py
agentstack_sdk/a2a/extensions/auth/oauth/oauth.py
agentstack_sdk/a2a/extensions/auth/oauth/storage/__init__.py
agentstack_sdk/a2a/extensions/auth/oauth/storage/base.py
agentstack_sdk/a2a/extensions/auth/oauth/storage/memory.py
agentstack_sdk/a2a/extensions/auth/secrets/__init__.py
agentstack_sdk/a2a/extensions/auth/secrets/secrets.py
agentstack_sdk/a2a/extensions/base.py
agentstack_sdk/a2a/extensions/common/__init__.py
agentstack_sdk/a2a/extensions/common/form.py
agentstack_sdk/a2a/extensions/exceptions.py
agentstack_sdk/a2a/extensions/services/__init__.py
agentstack_sdk/a2a/extensions/services/embedding.py
agentstack_sdk/a2a/extensions/services/form.py
agentstack_sdk/a2a/extensions/services/llm.py
agentstack_sdk/a2a/extensions/services/mcp.py
agentstack_sdk/a2a/extensions/services/platform.py
agentstack_sdk/a2a/extensions/tools/__init__.py
agentstack_sdk/a2a/extensions/tools/call.py
agentstack_sdk/a2a/extensions/tools/exceptions.py
agentstack_sdk/a2a/extensions/ui/__init__.py
agentstack_sdk/a2a/extensions/ui/agent_detail.py
agentstack_sdk/a2a/extensions/ui/canvas.py
agentstack_sdk/a2a/extensions/ui/citation.py
agentstack_sdk/a2a/extensions/ui/error.py
agentstack_sdk/a2a/extensions/ui/form_request.py
agentstack_sdk/a2a/extensions/ui/settings.py
agentstack_sdk/a2a/extensions/ui/trajectory.py
agentstack_sdk/a2a/types.py
agentstack_sdk/platform/__init__.py
agentstack_sdk/platform/client.py
agentstack_sdk/platform/common.py
agentstack_sdk/platform/configuration.py
agentstack_sdk/platform/context.py
agentstack_sdk/platform/file.py
agentstack_sdk/platform/model_provider.py
agentstack_sdk/platform/provider.py
agentstack_sdk/platform/provider_build.py
agentstack_sdk/platform/types.py
agentstack_sdk/platform/user.py
agentstack_sdk/platform/user_feedback.py
agentstack_sdk-0.5.0.dist-info/WHEEL
agentstack_sdk-0.5.0.dist-info/METADATA
agentstack_sdk-0.5.0.dist-info/RECORD
