Metadata-Version: 2.3
Name: agentstack-sdk
Version: 0.5.0
Summary: Agent Stack SDK
Author: IBM Corp.
Requires-Dist: a2a-sdk==0.3.21
Requires-Dist: objprint>=0.3.0
Requires-Dist: uvicorn>=0.35.0
Requires-Dist: asyncclick>=8.1.8
Requires-Dist: sse-starlette>=2.2.1
Requires-Dist: starlette>=0.47.2
Requires-Dist: anyio>=4.9.0
Requires-Dist: opentelemetry-api>=1.35.0
Requires-Dist: opentelemetry-exporter-otlp-proto-http>=1.35.0
Requires-Dist: opentelemetry-instrumentation-fastapi>=0.56b0
Requires-Dist: opentelemetry-sdk>=1.35.0
Requires-Dist: tenacity>=9.1.2
Requires-Dist: janus>=2.0.0
Requires-Dist: httpx
Requires-Dist: mcp>=1.12.3
Requires-Dist: fastapi>=0.116.1
Requires-Python: >=3.11, <3.14
